avri/__init__.py
avri/api.py
avri/endpoints.py
avri_api-0.1.8.dist-info/LICENSE
avri_api-0.1.8.dist-info/METADATA
avri_api-0.1.8.dist-info/WHEEL
avri_api-0.1.8.dist-info/top_level.txt
avri_api-0.1.8.dist-info/RECORD
