Metadata-Version: 2.1
Name: avri-api
Version: 0.1.8
Summary: Unofficial wrapper around Avri endpoints
Home-page: https://github.com/timvancann/pyavri
Author: Tim van Cann
Author-email: timvancann@gmail.com
License: UNKNOWN
Platform: UNKNOWN
Classifier: Programming Language :: Python :: 3
Classifier: License :: OSI Approved :: MIT License
Classifier: Operating System :: OS Independent
Requires-Python: >=3.7
Requires-Dist: requests (>=2.22.0)
Requires-Dist: pyfunctional (>=1.3.0)
